ipymongo/__init__.py
ipymongo/bak.py
ipymongo/client.py
ipymongo/collection.py
ipymongo/database.py
ipymongo/model.py
utest/__init__.py
i_pymongo-0.1.0.dist-info/LICENSE
i_pymongo-0.1.0.dist-info/METADATA
i_pymongo-0.1.0.dist-info/WHEEL
i_pymongo-0.1.0.dist-info/top_level.txt
i_pymongo-0.1.0.dist-info/RECORD
