Metadata-Version: 2.1
Name: i-pymongo
Version: 0.1.0
Summary: 
